deeprl/__init__.py
deeprl/agents/__init__.py
deeprl/agents/base_agent.py
deeprl/agents/policy_iteration_agent.py
deeprl/agents/q_learning_agent.py
deeprl/agents/value_iteration_agent.py
deeprl/environments/__init__.py
deeprl/environments/base_environment.py
deeprl/environments/gymnasium_env_wrapper.py
deeprl/evaluation/__init__.py
deeprl/evaluation/statistical_tests.py
deeprl/function_approximations/__init__.py
deeprl/function_approximations/base_approximator.py
deeprl/function_approximations/polynomial_basis_approximator.py
deeprl/function_approximations/radial_basis_approximator.py
deeprl/policies/__init__.py
deeprl/policies/base_policy.py
deeprl/policies/deterministic_policy.py
deeprl/policies/epsilon_greedy_decay_policy.py
deeprl/policies/epsilon_greedy_policy.py
deeprl/policies/softmax_policy.py
deeprl/reward_shaping/__init__.py
deeprl/reward_shaping/base_reward_shaping.py
deeprl/reward_shaping/default_reward.py
deeprl/reward_shaping/distance_based_shaping.py
deeprl/reward_shaping/mountain_car_reward_shaping.py
deeprl/reward_shaping/potential_based_shaping.py
deeprl/reward_shaping/step_penalty_shaping.py
deeprl/utils/__init__.py
deeprl/utils/data_module.py
deeprl/utils/hyperparameters.py
deeprl/utils/module.py
deeprl/utils/progress.py
deeprl/utils/trainer.py
deeprl/visualization/__init__.py
deeprl/visualization/progress_board.py
deeprlearn-0.1.0.dist-info/LICENSE
deeprlearn-0.1.0.dist-info/METADATA
deeprlearn-0.1.0.dist-info/WHEEL
deeprlearn-0.1.0.dist-info/top_level.txt
deeprlearn-0.1.0.dist-info/RECORD
