Metadata-Version: 2.1
Name: deeprlearn
Version: 0.1.0
Summary: A reinforcement learning library for clasic and deep reinforcement learning research.
Home-page: https://github.com/MaxGalindo150/deeprl
Author: Maximiliano Galindo
Author-email: maximilianogalindo7@gmail.com
License: MIT
Classifier: Programming Language :: Python :: 3
Classifier: License :: OSI Approved :: MIT License
Classifier: Operating System :: OS Independent
Classifier: Topic :: Scientific/Engineering :: Artificial Intelligence
Requires-Python: >=3.7
License-File: LICENSE
Requires-Dist: gymnasium >=0.27.0
Requires-Dist: torch >=1.10.0
Requires-Dist: numpy >=1.21.0
Requires-Dist: scikit-learn >=0.24.0
